ammber/BinarySystems.py
ammber/__init__.py
ammber/utils.py
ammber-0.1.7.dist-info/licenses/LICENSE.md
ammber-0.1.7.dist-info/METADATA
ammber-0.1.7.dist-info/WHEEL
ammber-0.1.7.dist-info/top_level.txt
ammber-0.1.7.dist-info/RECORD
