Metadata-Version: 2.4
Name: ammber
Version: 0.1.7
Summary: A Python package for parametrizing Gibbs free energy curves for phase-field modeling
Author-email: "W. Beck Andrews" <wband@umich.edu>, Xander Mensah <xmen@umich.edu>, Katsuyo Thornton <kthorn@umich.edu>
License-Expression: MIT
Project-URL: Homepage, https://github.com/UMThorntongroup/
Classifier: Development Status :: 1 - Planning
Classifier: Intended Audience :: Science/Research
Classifier: Programming Language :: Python :: 3
Requires-Python: <4,>=2.7
License-File: LICENSE.md
Requires-Dist: numpy<2.0
Requires-Dist: scipy
Requires-Dist: pycalphad
Dynamic: license-file
